bittencert/__init__.py
bittencert/cli.py
bittencert/client.py
bittencert/generate.py
bittencert/verify.py
bittencert-0.0.3.dist-info/LICENSE
bittencert-0.0.3.dist-info/METADATA
bittencert-0.0.3.dist-info/WHEEL
bittencert-0.0.3.dist-info/entry_points.txt
bittencert-0.0.3.dist-info/top_level.txt
bittencert-0.0.3.dist-info/RECORD
